xq_cloud/__init__.py
xq_cloud/backend.py
xq_cloud/client.py
xq_cloud/gates.py
xq_cloud/local_backend.py
xq_cloud/passes.py
xq_cloud/provider.py
xq_cloud/schemas.py
xq_cloud/transpiler.py
xq_cloud/util.py
xq_cloud-0.5.0.dist-info/WHEEL
xq_cloud-0.5.0.dist-info/entry_points.txt
xq_cloud-0.5.0.dist-info/METADATA
xq_cloud-0.5.0.dist-info/RECORD
