Metadata-Version: 2.3
Name: xq-cloud
Version: 0.5.0
Summary: Add your description here
Author: Pit Hüne
Author-email: Pit Hüne <pit@xeedq.com>
Requires-Dist: fastapi[standard]>=0.116.1
Requires-Dist: qiskit>=2.1.2
Requires-Dist: qiskit-aer>=0.17.1
Requires-Dist: sqlmodel>=0.0.25
Requires-Dist: requests>=2.31.0
Requires-Dist: xq-pulse
Requires-Python: >=3.10
